Workbook

Sheet Ganancias
B1: 2023 | C1: 2024
A2: enero | C2: =+'Ingresos 2024'!I15 -> 10110714
A3: febrero | B3: =+'Ingresos 2023'!J19 -> 2283600 | C3: =+'Ingresos 2024'!I122 -> 10469071
A4: marzo | B4: =+'Ingresos 2023'!J86 -> 15288600 | C4: =+'Ingresos 2024'!I269 -> 27516714
A5: abril | B5: =+'Ingresos 2023'!J158 -> 14433500 | G5: 2024 | H5: 110000000
A6: mayo | B6: =+'Ingresos 2023'!J236 -> 19622500 | G6: 2023 | H6: =160000000-70000000 -> 90000000
A7: junio | B7: =+'Ingresos 2023'!J325 -> 16771500 | G7: por lote | H7: =+H5+H6 -> 200000000 | K7: =+H7*100/60000000 -> 333.33333 | L7: %
A8: julio | B8: =+'Ingresos 2023'!J407 -> 14122500 | G8: por año | H8: =+H7/2 -> 100000000 | K8: =+H8*100/60000000 -> 166.66667 | L8: %
A9: agosto | B9: =+'Ingresos 2023'!J489 -> 16654000 | G9: por mes | H9: =+H8/12 -> 8333333.3 | K9: =+H9*100/60000000 -> 13.888889 | L9: %
A10: septiembre | B10: =+'Ingresos 2023'!J593 -> 7792000
A11: octubre | B11: =+'Ingresos 2023'!J681 -> 16975143
A12: noviembre | B12: =+'Ingresos 2023'!J799 -> 12457429 | G12: 2 gallineros cargados | I12: =+H9+H9*1.3/2 -> 13750000
A13: diciembre | B13: =+'Ingresos 2023'!J901 -> 8669714.3
E15: 13613000 | F15: ingreso mensual promedio 2000 aves
E16: =+E15/1800 -> 7562.7778 | F16: por plancha

Sheet Ingresos 2023
A1: Fecha | B1: Cliente | C1: Cantidad | D1: Concepto | E1: Precio Unitario | F1: Ventas | G1: Precio promedio
C2: =+SUM(C4:C1000) -> 17705 | F2: =+SUM(F3:F1000) -> 388554000 | G2: =+F2/C2 -> 21946.004
A3: 44953 | C3: 280 | D3: Bolsas de balanceado | E3: =+F3/C3 -> 500 | F3: 140000
A4: 44956 | C4: 10 | D4: C | E4: =+F4/C4 -> 15000 | F4: 150000
A5: 44957 | C5: 1 | D5: C | E5: =+F5/C5 -> 20000 | F5: 20000
A6: 44958 | C6: 11 | D6: C | E6: =+F6/C6 -> 18000 | F6: 198000 | G6: =+SUM(F6:F72)/SUM(C6:C72) -> 19769.011 | I6: Viajes | J6: 24
A7: 44959 | C7: 15 | D7: Huevo menudeo | E7: =+F7/C7 -> 666.66667 | F7: 10000
A8: 44962 | B8: Ani | C8: 10 | D8: B | E8: =+F8/C8 -> 18000 | F8: 180000 | I8: Costos | L8: Precios
A9: 44963 | B9: Coti | C9: 35 | D9: C | E9: =+F9/C9 -> 17000 | F9: 595000 | I9: Viajes | J9: =60/100*9*M9*J6 -> 972000 | L9: Combustible | M9: 7500 | N9: Gs/L
A10: 44963 | B10: Fredi | C10: 15 | D10: B | E10: =+F10/C10 -> 19000 | F10: 285000 | I10: Cubetas | J10: =+SUM(C6:C72)*M10 -> 526000 | L10: Cubetas | M10: 500 | N10: Gs/unidad
A11: 44964 | B11: Kiti | C11: 5 | D11: C | E11: =+F11/C11 -> 17800 | F11: 89000 | I11: Balanceado | J11: =8.6*28*M11 -> 15170400 | L11: Balanceado | M11: 63000 | N11: Gs/bolsa
B12: Luz Villasanti | C12: 3 | D12: B | E12: =+F12/C12 -> 20000 | F12: 60000 | I12: Personales | J12: =+M12*28 -> 1680000 | L12: Personal | M12: 60000 | N12: Gs/dia
B13: Ani | C13: 3 | D13: B | E13: =+F13/C13 -> 18000 | F13: 54000 | I13: Agua | J13: 15000
A14: 44965 | B14: Ani | C14: 5 | D14: B | E14: =+F14/C14 -> 18000 | F14: 90000 | I14: Vitaminas, etc | J14: 150000
A15: 44967 | B15: Vecinos | C15: 1 | D15: B | E15: =+F15/C15 -> 20000 | F15: 20000 | I15: TOTAL COSTOS | J15: =+SUM(J9:J14) -> 18513400
B16: Panadería | C16: 2 | D16: B | E16: =+F16/C16 -> 21000 | F16: 42000
B17: Ña Ernesta | C17: 10 | D17: B | E17: =+F17/C17 -> 20000 | F17: 200000 | I17: TOTAL INGRESOS | J17: =+SUM(F6:F72) -> 20797000
B18: Vecinos | C18: 2 | D18: Huevo picado | E18: =+F18/C18 -> 10000 | F18: 20000
B19: Coti | C19: 25 | D19: C | E19: =+F19/C19 -> 17000 | F19: 425000 | I19: TOTAL GANANCIA | J19: =+J17-J15 -> 2283600
A20: 44969 | B20: Edelio | C20: 3 | D20: C | E20: =+F20/C20 -> 18000 | F20: 54000
A21: 44970 | B21: Ani | C21: 5 | D21: B | E21: =+F21/C21 -> 18000 | F21: 90000
B22: Dalila | C22: 50 | D22: B | E22: =+F22/C22 -> 20000 | F22: 1000000
B23: Fredi | C23: 22 | D23: B | E23: =+F23/C23 -> 19000 | F23: 418000
A24: 44971 | B24: Fredi | C24: 22 | D24: B | E24: =+F24/C24 -> 19000 | F24: 418000
B25: Ña Oso | C25: 5 | D25: A | E25: =+F25/C25 -> 21000 | F25: 105000
A26: 44972 | B26: Vecinos | C26: 1 | D26: Huevo picado | E26: =+F26/C26 -> 10000 | F26: 10000
B27: Coti | C27: 45 | D27: C | E27: =+F27/C27 -> 17000 | F27: 765000 | J27: falta pagar 281000
A28: 44973 | B28: Elsa | C28: 6 | D28: C | E28: =+F28/C28 -> 19000 | F28: 114000
B29: Fredi | C29: 12 | D29: B | E29: =+F29/C29 -> 19000 | F29: 228000
B30: Dalila | C30: 50 | D30: B | E30: =+F30/C30 -> 20000 | F30: 1000000
C31: 2 | D31: S | E31: =+F31/C31 -> 22000 | F31: 44000
C32: 4 | D32: A | E32: =+F32/C32 -> 20000 | F32: 80000
C33: 3 | D33: B | E33: =+F33/C33 -> 20000 | F33: 60000
A34: 44974 | B34: Fredi | C34: 25 | D34: B | E34: =+F34/C34 -> 19000 | F34: 475000
B35: Blanqui | C35: 24 | D35: C | E35: =+F35/C35 -> 19000 | F35: 456000
B36: Blanqui | C36: 40 | D36: B | E36: =+F36/C36 -> 20000 | F36: 800000
B37: Magali Ovelar | C37: 2 | D37: A | E37: =+F37/C37 -> 22000 | F37: 44000
A38: 44975 | B38: Ña Ernesta | C38: 10 | D38: A | E38: =+F38/C38 -> 22000 | F38: 220000
B39: Fredi | C39: 20 | D39: B | E39: =+F39/C39 -> 20000 | F39: 400000
B40: Blanqui | C40: 25 | D40: B | E40: =+F40/C40 -> 20000 | F40: 500000
B41: Blanqui | C41: 5 | D41: C | E41: =+F41/C41 -> 19000 | F41: 95000
A42: 44976 | B42: Ani | C42: 6 | D42: C | E42: =+F42/C42 -> 18000 | F42: 108000
B43: Zuni SM | C43: 4 | D43: C | E43: =+F43/C43 -> 20000 | F43: 80000
B44: Antonio Guayaki | C44: 5 | D44: A | E44: =+F44/C44 -> 22000 | F44: 110000
B45: Pato | C45: 20 | D45: B | E45: =+F45/C45 -> 20000 | F45: 400000 | J45: falta cobrar
A46: 44977 | B46: Dalila | C46: 50 | D46: B | E46: =+F46/C46 -> 20000 | F46: 1000000
B47: Esteban | C47: 15 | D47: A | E47: =+F47/C47 -> 22000 | F47: 330000
B48: Esteban | C48: 7 | D48: B | E48: =+F48/C48 -> 21000 | F48: 147000
B49: Esteban | C49: 5 | D49: C | E49: =+F49/C49 -> 20000 | F49: 100000
A50: 44978 | B50: Blanqui | C50: 43 | D50: B | E50: 20000 | F50: =+E50*C50 -> 860000
B51: Fredi | C51: 13 | D51: A | E51: 20000 | F51: =+E51*C51 -> 260000
A52: 44979 | B52: Dalila | C52: 40 | D52: B | E52: 20000 | F52: =+E52*C52 -> 800000
B53: Ña Oso | C53: 5 | D53: A | E53: 22000 | F53: =+E53*C53 -> 110000
B54: Vecinos | C54: 3 | D54: C | E54: 20000 | F54: =+E54*C54 -> 60000
A55: 44980 | B55: Fredi | C55: 40 | D55: S | E55: 21000 | F55: =+E55*C55 -> 840000
B56: Dulce Anita | C56: 6 | D56: B | E56: 20000 | F56: =+E56*C56 -> 120000
B57: Tia Primi | C57: 2 | D57: A | E57: 22000 | F57: =+E57*C57 -> 44000
A58: 44981 | B58: Vecinos | C58: 5 | D58: C | E58: 20000 | F58: =+E58*C58 -> 100000
B59: Elsa | C59: 3 | D59: C | E59: 20000 | F59: =+E59*C59 -> 60000
B60: Chili | C60: 3 | D60: A | E60: 25000 | F60: =+E60*C60 -> 75000
A61: 44982 | B61: Blanqui | C61: 50 | D61: B | E61: 20000 | F61: =+E61*C61 -> 1000000
B62: Fredi | C62: 30 | D62: B | E62: 21000 | F62: =+E62*C62 -> 630000
B63: Fredi | C63: 10 | D63: A | E63: 22000 | F63: =+E63*C63 -> 220000
B64: Mari uñas | C64: 3 | D64: A | E64: 25000 | F64: =+E64*C64 -> 75000
A65: 44984 | B65: Dalila | C65: 68 | D65: B | E65: 23000 | F65: =+E65*C65 -> 1564000
A66: 44985 | B66: Fredi | C66: 30 | D66: B | E66: 22000 | F66: =+E66*C66 -> 660000
B67: Fredi | C67: 3 | D67: C | E67: 21000 | F67: =+E67*C67 -> 63000
B68: Santiago | C68: 23 | D68: B | E68: 22000 | F68: =+E68*C68 -> 506000
B69: Santiago | C69: 14 | D69: A | E69: 23000 | F69: =+E69*C69 -> 322000
B70: Xtina | C70: 11 | D70: A | E70: 22000 | F70: =+E70*C70 -> 242000
B71: Ña Ernesta | C71: 9 | D71: A | E71: 23000 | F71: =+E71*C71 -> 207000
B72: Edelio | C72: 3 | D72: C | E72: 20000 | F72: =+E72*C72 -> 60000
A73: 44986 | B73: Vecinos | C73: 6 | D73: B | E73: 23000 | F73: =+E73*C73 -> 138000 | G73: =+SUM(F73:F144)/SUM(C73:C144) -> 24223.092 | I73: Viajes | J73: 22
A74: 44987 | B74: Fredi | C74: 40 | D74: A | E74: 23000 | F74: =+E74*C74 -> 920000
A75: 44988 | B75: Coti | C75: 45 | D75: A | E75: 23000 | F75: =+E75*C75 -> 1035000 | I75: Costos | L75: Precios
B76: Santiago | C76: 36 | D76: B | E76: 22000 | F76: =+E76*C76 -> 792000 | I76: Viajes | J76: =60/100*9*M76*J73 -> 891000 | L76: Combustible | M76: 7500 | N76: Gs/L
B77: Vecinos | C77: 5 | D77: B | E77: 23000 | F77: =+E77*C77 -> 115000 | I77: Cubetas | J77: =+SUM(C73:C144)*M77 -> 766500 | L77: Cubetas | M77: 500 | N77: Gs/unidad
A78: 44989 | B78: Fredi | C78: =18+22 -> 40 | D78: A | E78: 23000 | F78: =+E78*C78 -> 920000 | I78: Balanceado | J78: =9.3*31*M78 -> 18162900 | L78: Balanceado | M78: 63000 | N78: Gs/bolsa
B79: Tia Lourdes | C79: 3 | D79: S | E79: 25000 | F79: =+E79*C79 -> 75000 | I79: Personales | J79: =+M79*31 -> 1860000 | L79: Personal | M79: 60000 | N79: Gs/dia
B80: Ña Oso | C80: 5 | D80: A | E80: 23000 | F80: =+E80*C80 -> 115000 | I80: Agua | J80: 15000
B81: Alianza | C81: 20 | D81: A | E81: 23000 | F81: =+E81*C81 -> 460000 | I81: Vitaminas, etc | J81: 150000
B82: Ña Ernesta | C82: 10 | D82: B | E82: 23000 | F82: =+E82*C82 -> 230000 | I82: TOTAL COSTOS | J82: =+SUM(J76:J81) -> 21845400
A83: 44991 | B83: Ña Ingrid | C83: 4 | D83: A | E83: 23000 | F83: =+E83*C83 -> 92000
B84: Fredi | C84: 20 | D84: A | E84: 23000 | F84: =+E84*C84 -> 460000 | I84: TOTAL INGRESOS | J84: =+SUM(F73:F144) -> 37134000
B85: Tia Primi | C85: 2 | D85: S | E85: 24000 | F85: =+E85*C85 -> 48000
B86: Fada | C86: =35+39 -> 74 | D86: A | E86: 23000 | F86: =+E86*C86 -> 1702000 | I86: TOTAL GANANCIA | J86: =+J84-J82 -> 15288600
A87: 44992 | B87: Vecinos | C87: 3 | D87: B | E87: 22000 | F87: =+E87*C87 -> 66000
A88: 44993 | B88: Santiago | C88: 50 | D88: A | E88: 23000 | F88: =+E88*C88 -> 1150000
B89: Alison | C89: 80 | D89: A | E89: 23000 | F89: =+E89*C89 -> 1840000
B90: Profes FCQ | C90: 2 | D90: S | E90: 25000 | F90: =+E90*C90 -> 50000
B91: Fredi | C91: 20 | D91: A | E91: 23000 | F91: =+E91*C91 -> 460000
A92: 44994 | B92: Santiago | C92: 20 | D92: A | E92: 23000 | F92: =+E92*C92 -> 460000
A93: 44997 | B93: Antonio Guayaki | C93: 10 | D93: A | E93: 25000 | F93: =+E93*C93 -> 250000
B94: Ña Ernesta | C94: 10 | D94: S | E94: 25000 | F94: =+E94*C94 -> 250000
B95: Vecinos | C95: 3 | D95: A | E95: 25000 | F95: =+E95*C95 -> 75000
B96: Alison | C96: 113 | D96: A | E96: 23000 | F96: =+E96*C96 -> 2599000
A97: 44999 | B97: Fredi | C97: 30 | D97: A | E97: 25000 | F97: =+E97*C97 -> 750000
B98: Dalila | C98: 15 | D98: A | E98: 25000 | F98: =+E98*C98 -> 375000
B99: Vecinos | C99: 1 | D99: C | E99: 22000 | F99: =+E99*C99 -> 22000
B100: Esteban | C100: 10 | D100: A | E100: 25000 | F100: =+E100*C100 -> 250000
...

Sheet Ingresos 2024
A1: Fecha | B1: Cliente | C1: Cantidad | D1: Concepto | E1: Precio Unitario | F1: Ingreso | G1: Precio promedio
A2: 45293 | B2: Marian Elenice | C2: 20 | D2: A | E2: 21000 | F2: =+E2*C2 -> 420000 | G2: =+SUM(F2:F108)/SUM(C2:C108) -> 19249.709 | H2: Viajes | I2: 30
B3: Ysapy | C3: 5 | D3: S | E3: 23000 | F3: =+E3*C3 -> 115000
B4: Agus | C4: 3 | D4: S | E4: 22000 | F4: =+E4*C4 -> 66000 | H4: Costos | K4: Precios
B5: Fredi | C5: 20 | D5: S | E5: 21000 | F5: =+E5*C5 -> 420000 | H5: Viajes | I5: =60/100*9*L5*I2 -> 1215000 | K5: Combustible | L5: 7500 | M5: Gs/L
B6: Fada | C6: 45 | D6: A | E6: 20000 | F6: =+E6*C6 -> 900000 | H6: Cubetas | I6: =+SUM(C2:C108)*L6 -> 859000 | K6: Cubetas | L6: 500 | M6: Gs/unidad
B7: Dalila | C7: 40 | D7: A | E7: 20000 | F7: =+E7*C7 -> 800000 | H7: Balanceado | I7: =+L7*9*31 -> 17577000 | K7: Balanceado | L7: 63000 | M7: Gs/bolsa
B8: Dalila | C8: 15 | D8: S | E8: 21000 | F8: =+E8*C8 -> 315000 | H8: Personales | I8: =+L8*31 -> 3144285.7 | K8: Personal | L8: =500000/7+30000 -> 101428.57 | M8: Gs/dia
A9: 45294 | B9: Coti | C9: 25 | D9: A | E9: 19000 | F9: =+E9*C9 -> 475000 | H9: Agua | I9: 15000
A10: 45295 | B10: Derlis Paredes | C10: 12 | D10: S | E10: 21000 | F10: =+E10*C10 -> 252000 | H10: Vitaminas, etc | I10: 150000
B11: Marian Elenice | C11: 20 | D11: A | E11: 21000 | F11: =+E11*C11 -> 420000 | H11: TOTAL COSTOS | I11: =+SUM(I5:I10) -> 22960286
B12: Abner | C12: 6 | D12: J | E12: 24000 | F12: =+E12*C12 -> 144000
B13: Dalila | C13: 11 | D13: S | E13: 21000 | F13: =+E13*C13 -> 231000 | H13: TOTAL INGRESOS | I13: =+SUM(F2:F108) -> 33071000
B14: Dalila | C14: 35 | D14: A | E14: 20000 | F14: =+E14*C14 -> 700000
B15: Kiti | C15: 25 | D15: B | E15: 20000 | F15: =+E15*C15 -> 500000 | H15: TOTAL GANACIA | I15: =+I13-I11 -> 10110714
A16: 45297 | B16: Pastora | C16: 5 | D16: J | E16: 24000 | F16: =+E16*C16 -> 120000
B17: Noelia | C17: 8 | D17: B | E17: 20000 | F17: =+E17*C17 -> 160000
B18: Fredi | C18: 15 | D18: S | E18: 21000 | F18: =+E18*C18 -> 315000
B19: Dalila | C19: 40 | D19: A | E19: 20000 | F19: =+E19*C19 -> 800000
B20: Dalila | C20: 6 | D20: S | E20: 21000 | F20: =+E20*C20 -> 126000
B21: Despensa Lucero | C21: 5 | D21: A | E21: 21000 | F21: =+E21*C21 -> 105000
B22: Agus | C22: 3 | D22: A | E22: 21000 | F22: =+E22*C22 -> 63000
B23: Ysapy | C23: 4 | D23: A | E23: 22000 | F23: =+E23*C23 -> 88000
A24: 45298 | B24: Coti | C24: 22 | D24: A | E24: 20000 | F24: =+E24*C24 -> 440000
B25: Coti | C25: 6 | D25: B | E25: 18000 | F25: =+E25*C25 -> 108000
A26: 45299 | B26: Fada | C26: 50 | D26: A | E26: 20000 | F26: =+E26*C26 -> 1000000
B27: Ingrid | C27: 6 | D27: A | E27: 22000 | F27: =+E27*C27 -> 132000
A28: 45300 | B28: Alianza | C28: 15 | D28: S | E28: 23000 | F28: =+E28*C28 -> 345000
B29: Marian Elenice | C29: 15 | D29: A | E29: 21000 | F29: =+E29*C29 -> 315000
B30: Fredi | C30: 18 | D30: S | E30: 21000 | F30: =+E30*C30 -> 378000
C31: 100 | D31: BOLSAS | E31: 500 | F31: =+E31*C31 -> 50000
A32: 45301 | B32: Derlis Paredes | C32: 15 | D32: S | E32: 21000 | F32: =+E32*C32 -> 315000
B33: Agus | C33: 3 | D33: S | E33: 22000 | F33: =+E33*C33 -> 66000
B34: Dalila | C34: 47 | D34: A | E34: 20000 | F34: =+E34*C34 -> 940000
B35: Benito | C35: 15 | D35: A | E35: 20000 | F35: =+E35*C35 -> 300000
A36: 45302 | B36: Coti | C36: 20 | D36: A | E36: 20000 | F36: =+E36*C36 -> 400000
B37: Coti | C37: 13 | D37: B | E37: 18000 | F37: =+E37*C37 -> 234000
A38: 45303 | B38: Zuni SM | C38: 3 | D38: A | E38: 22000 | F38: =+E38*C38 -> 66000
B39: Vecinos | C39: 1 | D39: B | E39: 20000 | F39: =+E39*C39 -> 20000
B40: Ysapy | C40: 4 | D40: S | E40: 23000 | F40: =+E40*C40 -> 92000
B41: Fada | C41: 44 | D41: A | E41: 20000 | F41: =+E41*C41 -> 880000
B42: Arguello | C42: 2 | D42: S | E42: 25000 | F42: =+E42*C42 -> 50000
A43: 45305 | B43: Coti | C43: 6 | D43: B | E43: 18000 | F43: =+E43*C43 -> 108000
B44: Coti | C44: 20 | D44: A | E44: 20000 | F44: =+E44*C44 -> 400000
A45: 45306 | B45: Kiti | C45: 5 | D45: S | E45: 22000 | F45: =+E45*C45 -> 110000
B46: Kiti | C46: 2 | D46: B | E46: 20000 | F46: =+E46*C46 -> 40000
A47: 45307 | B47: Fada | C47: 50 | D47: A | E47: 20000 | F47: =+E47*C47 -> 1000000
B48: Ingrid | C48: 6 | D48: A | E48: 22000 | F48: =+E48*C48 -> 132000
B49: Irma Lopez | C49: 4 | D49: S | E49: 23000 | F49: =+E49*C49 -> 92000
B50: Dalila | C50: 52 | D50: A | E50: 20000 | F50: =+E50*C50 -> 1040000
A51: 45308 | B51: Coti | C51: 10 | D51: B | E51: 18000 | F51: =+E51*C51 -> 180000
B52: Coti | C52: 20 | D52: A | E52: 20000 | F52: =+E52*C52 -> 400000
A53: 45308 | B53: Derlis Paredes | C53: 15 | D53: S | E53: 21000 | F53: =+E53*C53 -> 315000
B54: Vecinos | C54: 3 | D54: A | E54: 20000 | F54: =+E54*C54 -> 60000
B55: Agus | C55: 3 | D55: J | E55: 23000 | F55: =+E55*C55 -> 69000
A56: 45309 | B56: Alianza | C56: 15 | D56: S | E56: 23000 | F56: =+E56*C56 -> 345000
B57: Fredi | C57: 20 | D57: S | E57: 21000 | F57: =+E57*C57 -> 420000
B58: Chiqui Lopez | C58: 10 | D58: A | E58: 21000 | F58: =+E58*C58 -> 210000
B59: Fada | C59: 29 | D59: A | E59: 20000 | F59: =+E59*C59 -> 580000
A60: 45310 | B60: Lomiteria | C60: 2 | D60: A | E60: 22000 | F60: =+E60*C60 -> 44000
B61: Albañiles | C61: 4 | D61: A | E61: 20000 | F61: =+E61*C61 -> 80000
C62: 2 | D62: S | E62: 23000 | F62: =+E62*C62 -> 46000
A63: 45311 | B63: Pastora | C63: 3 | D63: S | E63: 24000 | F63: =+E63*C63 -> 72000
B64: Ysapy | C64: 4 | D64: S | E64: 23000 | F64: =+E64*C64 -> 92000
B65: Benito | C65: 10 | D65: A | E65: 21000 | F65: =+E65*C65 -> 210000
B66: Dalila | C66: 36 | D66: A | E66: 20000 | F66: =+E66*C66 -> 720000
B67: Dalila | C67: 6 | D67: S | E67: 21000 | F67: =+E67*C67 -> 126000
B68: Despensa Lucero | C68: 5 | D68: A | E68: 22000 | F68: =+E68*C68 -> 110000
B69: Abner | C69: 5 | D69: J | E69: 24000 | F69: =+E69*C69 -> 120000
B70: Lomiteria | C70: 3 | D70: S | E70: 22000 | F70: =+E70*C70 -> 66000
A71: 45312 | B71: Promo 84 | C71: 13 | D71: S | E71: 23000 | F71: =+E71*C71 -> 299000
A72: 45313 | B72: Dalila | C72: 70 | D72: A | E72: 20000 | F72: =+E72*C72 -> 1400000
B73: Fredi | C73: 15 | D73: S | E73: 21000 | F73: =+E73*C73 -> 315000
B74: Ernesta | C74: 10 | D74: A | E74: 22000 | F74: =+E74*C74 -> 220000
B75: Achi | C75: 3 | D75: A | E75: 22000 | F75: =+E75*C75 -> 66000
B76: Lomiteria | C76: 3 | D76: A | E76: 22000 | F76: =+E76*C76 -> 66000
B77: Vecinos | C77: 1 | D77: A | E77: 20000 | F77: =+E77*C77 -> 20000
A78: 45314 | B78: Coti | C78: 30 | D78: A | E78: 20000 | F78: =+E78*C78 -> 600000
B79: Coti | C79: 10 | D79: B | E79: 18000 | F79: =+E79*C79 -> 180000
A80: 45315 | B80: Lomiteria | C80: 4 | D80: A | E80: 22000 | F80: =+E80*C80 -> 88000
B81: Vecinos | C81: 1 | D81: S | E81: 23000 | F81: =+E81*C81 -> 23000
B82: Ingrid | C82: 6 | D82: A | E82: 22000 | F82: =+E82*C82 -> 132000
A83: 45316 | B83: Derlis Paredes | C83: 15 | D83: S | E83: 21000 | F83: =+E83*C83 -> 315000
B84: Ysapy | C84: 4 | D84: S | E84: 23000 | F84: =+E84*C84 -> 92000
B85: Fada | C85: 54 | D85: A | E85: 20000 | F85: =+E85*C85 -> 1080000
B86: Agus | C86: 4 | D86: S | E86: 22000 | F86: =+E86*C86 -> 88000
B87: Vecinos | C87: 1 | D87: A | E87: 22000 | F87: =+E87*C87 -> 22000
C88: 45 | D88: GALLINAZA | E88: 18000 | F88: =+E88*C88 -> 810000
A89: 45317 | B89: Albañiles | C89: 3 | D89: A | E89: 22000 | F89: =+E89*C89 -> 66000
A90: 45318 | B90: Ernesta | C90: 10 | D90: A | E90: 23000 | F90: =+E90*C90 -> 230000
B91: Fredi | C91: 20 | D91: S | E91: 21000 | F91: =+E91*C91 -> 420000
A92: 45318 | B92: Coti | C92: 30 | D92: A | E92: 20000 | F92: =+E92*C92 -> 600000
B93: Coti | C93: 20 | D93: B | E93: 18000 | F93: =+E93*C93 -> 360000
B94: Lomiteria | C94: 5 | D94: B | E94: 20000 | F94: =+E94*C94 -> 100000
A95: 45319 | B95: Vecinos | C95: 2 | D95: A | E95: 22000 | F95: =+E95*C95 -> 44000
A96: 45320 | B96: Fredi | C96: 20 | D96: S | E96: 22000 | F96: =+E96*C96 -> 440000
B97: Dalila | C97: 80 | D97: A | E97: 20000 | F97: =+E97*C97 -> 1600000
A98: 45321 | B98: Ingrid | C98: 8 | D98: A | E98: 22000 | F98: =+E98*C98 -> 176000
A99: 45322 | B99: Derlis Paredes | C99: 15 | D99: S | E99: 21000 | F99: =+E99*C99 -> 315000
B100: Ysapy | C100: 3 | D100: S | E100: 23000 | F100: =+E100*C100 -> 69000
...

Sheet Egresos
A1: Fecha | B1: Concepto | C1: Cantidad | D1: Precio Unitario | E1: Cliente | F1: Observaciones
A3: 44805 | B3: Cascarilla de arroz | C3: 1 | D3: 2600000
A4: 44816 | B4: AVT 40 | C4: 1 | D4: 160000 | E4: Cooka
A5: 44816 | B5: Poly-phen | C5: 1 | D5: 348000 | E5: Bionatural
A6: 44816 | B6: Potenbac polvo 100g | C6: 1 | D6: 157000 | E6: Bionatural
A7: 44816 | B7: Cables y portafoco
A8: 44817 | B8: Carpa negra 15x4
A9: 44788 | B9: Diluyente | C9: 2 | D9: 35000 | E9: Bionatural
A10: 44820 | B10: Pollitas HyLine Brown | C10: 2000 | D10: =+[1]Egresos!E10/C10 -> 0
A11: 44820 | B11: Balanceado Inicio | C11: 10 | D11: =+[1]Egresos!E11/C11 -> #VALUE! | E11: Cooka
A12: 44820 | B12: Maiz molido 30 kg | C12: 1 | E12: Cooka
A13: 44820 | B13: Stop Stress | C13: 1 | D13: 245000 | E13: Cooka
A14: 44820 | B14: Balanza miligramo
A15: 44820 | B15: Balde para agua | C15: 2 | D15: =+[1]Egresos!E15/C15 -> 0
A16: 44820 | B16: Balde para agua | C16: 2 | D16: =+[1]Egresos!E16/C16 -> 0
A17: 44826 | B17: Vacunas
A18: 44826 | B18: Balanceado Inicio | C18: 15 | D18: =+[1]Egresos!E18/C18 -> 0
A19: 44827 | B19: Personal vacunación | C19: 2 | D19: 30000
A20: 44834 | B20: Balanceado Inicio | C20: 20 | D20: =+[1]Egresos!E20/C20 -> 0
A21: 44834 | B21: Vacunas
A22: 44834 | B22: Personal control | C22: 2 | D22: 60000
A23: 44840 | B23: Bebederos pendulares | C23: 6 | D23: =+[1]Egresos!E23/C23 -> 0
A24: 44841 | B24: Vacunas
A25: 44841 | B25: Balanceado Inicio | C25: 18 | D25: =+[1]Egresos!E25/C25 -> 0
A26: 44845 | B26: Personal vacunación | C26: 2 | D26: 30000
A27: 44848 | B27: Vacunas
A28: 44848 | B28: Balanceado Inicio | C28: 20 | D28: =+[1]Egresos!E28/C28 -> 0
A29: 44849 | B29: Vacunas
A30: 44852 | B30: Bebederos pendulares | C30: 8 | D30: =+[1]Egresos!E30/C30 -> 0
A31: 44855 | B31: Balanceado Inicio | C31: 20 | D31: =+[1]Egresos!E31/C31 -> 0
A32: 44860 | B32: Despique | C32: 2000 | D32: =+[1]Egresos!E32/C32 -> 0
A33: 44860 | B33: Personal despique | C33: 1 | D33: 60000
A34: 44862 | B34: Balanceado Inicio | C34: 25 | D34: =+[1]Egresos!E34/C34 -> 0
A35: 44866 | B35: Febenlasca 1L | C35: 1 | D35: =+[1]Egresos!E35/C35 -> 0
A36: 44869 | B36: Balanceado Inicio | C36: 30 | D36: =+[1]Egresos!E36/C36 -> 0
A37: 44877 | B37: Balanceado Crecimiento | C37: 25 | D37: =+[1]Egresos!E37/C37 -> 0
A38: 44883 | B38: Balanceado Crecimiento | C38: 35 | D38: =+[1]Egresos!E38/C38 -> 0
A39: 44891 | B39: Balanceado Crecimiento | C39: 30 | D39: =+[1]Egresos!E39/C39 -> 0
A40: 44893 | B40: Bolsas de balanceado | C40: 200 | D40: =+#REF!/C40 -> #REF! | E40: Venialvos
A41: 44897 | B41: Balanceado Crecimiento | C41: 35 | D41: =+[1]Egresos!E41/C41 -> 0
A42: 44901 | B42: Bolsas de balanceado | C42: 100 | D42: =+#REF!/C42 -> #REF!
A43: 44904 | B43: Balanceado Crecimiento | C43: 42 | D43: =+[1]Egresos!E43/C43 -> 0
A44: 44912 | B44: Balanceado Crecimiento | C44: 42 | D44: =+[1]Egresos!E44/C44 -> 0
A45: 44916 | B45: Balanceado Crecimiento | C45: 42 | D45: =+[1]Egresos!E45/C45 -> 0
A46: 44924 | B46: Balanceado Crecimiento | C46: 42 | D46: =+[1]Egresos!E46/C46 -> 0
A47: 44932 | B47: Balanceado Crecimiento | C47: 42 | D47: =+[1]Egresos!E47/C47 -> 0
A48: 44939 | B48: Balanceado Crecimiento | C48: 48 | D48: =+[1]Egresos!E48/C48 -> 0
A49: 44946 | B49: Balanceado Crecimiento | C49: 52 | D49: =+[1]Egresos!E49/C49 -> 0
A50: 44950 | B50: Promotor L47 1 L | C50: 1 | D50: =+[1]Egresos!E50/C50 -> 0
A51: 44953 | B51: Bolsas de balanceado | C51: 280 | D51: =+#REF!/C51 -> #REF!
A52: 44954 | B52: Balanceado Ponedora | C52: 50 | D52: =+[1]Egresos!E52/C52 -> 0
A53: 44956 | B53: Huevo C | C53: 10 | D53: =+#REF!/C53 -> #REF!
A54: 44957 | B54: Huevo C | C54: 1 | D54: =+#REF!/C54 -> #REF!
A55: 44958 | B55: Huevo C | C55: 11 | D55: =+#REF!/C55 -> #REF!
A56: 44959 | B56: Huevo menudeo | C56: 15 | D56: =+#REF!/C56 -> #REF!
A57: 44960 | B57: Balanceado Ponedora | C57: 52 | D57: =+[1]Egresos!E57/C57 -> 0
A58: 44962 | B58: Huevo B | C58: 10 | D58: =+#REF!/C58 -> #REF! | E58: Ani
A59: 44963 | B59: Huevo C | C59: 35 | D59: =+#REF!/C59 -> #REF! | E59: Coti
A60: 44963 | B60: Locote | C60: 124 | D60: =+#REF!/C60 -> #REF! | E60: Oscar
A61: 44963 | B61: Huevo B | C61: 15 | D61: =+#REF!/C61 -> #REF! | E61: Fredi
A62: 44963 | B62: Locote | C62: 5 | D62: =+#REF!/C62 -> #REF! | E62: Fredi
A63: 44963 | B63: Locote | C63: 5 | D63: =+#REF!/C63 -> #REF! | E63: Kiti
A64: 44964 | B64: Locote | C64: 11.5 | D64: =+#REF!/C64 -> #REF! | E64: Kiti
A65: 44964 | B65: Huevo C | C65: 5 | D65: =+#REF!/C65 -> #REF! | E65: Kiti
A66: 44964 | B66: Locote | C66: 20 | D66: =+#REF!/C66 -> #REF! | E66: Ani
A67: 44964 | B67: Huevo B | C67: 3 | D67: =+#REF!/C67 -> #REF! | E67: Luz Villasanti
A68: 44964 | B68: Huevo B | C68: 3 | D68: =+#REF!/C68 -> #REF! | E68: Ani
A69: 44965 | B69: Huevo B | C69: 5 | D69: =+#REF!/C69 -> #REF! | E69: Ani
... A72: 44967 | B72: Huevo B | C72: 10 | D72: =+#REF!/C72 -> #REF! | E72: Ña Ernesta
A73: 44967 | B73: Balanceado Ponedora | C73: 60 | D73: =+[1]Egresos!E73/C73 -> #VALUE! | E73: Cooka
A74: 44967 | B74: Cubetas | C74: =2*100 -> 200 | D74: =+[1]Egresos!E74/C74 -> #VALUE! | E74: Cooka
A75: 44967 | B75: Huevo picado | C75: 2 | D75: =+#REF!/C75 -> #REF! | E75: Vecinos
A76: 44967 | B76: Huevo C | C76: 25 | D76: =+#REF!/C76 -> #REF! | E76: Coti
A77: 44969 | B77: Huevo C | C77: 3 | D77: =+#REF!/C77 -> #REF! | E77: Edelio
A78: 44970 | B78: Locote | C78: 162 | D78: =+#REF!/C78 -> #REF! | E78: Walter
A79: 44970 | B79: Huevo B | C79: 5 | D79: =+#REF!/C79 -> #REF! | E79: Ani
A80: 44970 | B80: Huevo B | C80: 50 | D80: =+#REF!/C80 -> #REF! | E80: Dalila
A81: 44970 | B81: Huevo B | C81: 22 | D81: =+#REF!/C81 -> #REF! | E81: Fredi
A82: 44971 | B82: Huevo B | C82: 22 | D82: =+#REF!/C82 -> #REF! | E82: Fredi
A83: 44971 | B83: Huevo A | C83: 5 | D83: =+#REF!/C83 -> #REF! | E83: Ña Oso
A84: 44972 | B84: Huevo picado | C84: 1 | D84: =+#REF!/C84 -> #REF! | E84: Vecinos
A85: 44972 | B85: Cubeta blanca | C85: 200 | D85: =+[1]Egresos!E85/C85 -> #VALUE! | E85: Cooka
A86: 44972 | B86: Cubeta verde | C86: 210 | D86: =+[1]Egresos!E86/C86 -> #VALUE! | E86: Coti
A87: 44972 | B87: Huevo C | C87: 45 | D87: =+#REF!/C87 -> #REF! | E87: Coti | F87: falta pagar 281000
A88: 44973 | B88: Huevo C | C88: 6 | D88: =+#REF!/C88 -> #REF! | E88: Elsa
A89: 44973 | B89: Locote | C89: 15 | D89: =+#REF!/C89 -> #REF! | E89: Elsa
A90: 44973 | B90: Huevo B | C90: 12 | D90: =+#REF!/C90 -> #REF! | E90: Fredi
A91: 44973 | B91: Locote | C91: 5 | D91: =+#REF!/C91 -> #REF! | E91: Fredi
A92: 44973 | B92: Huevo B | C92: 50 | D92: =+#REF!/C92 -> #REF! | E92: Dalila
A93: 44973 | B93: Huevo S | C93: 2 | D93: =+#REF!/C93 -> #REF!
A94: 44973 | B94: Huevo A | C94: 4 | D94: =+#REF!/C94 -> #REF!
A95: 44973 | B95: Huevo B | C95: 3 | D95: =+#REF!/C95 -> #REF!
A96: 44974 | B96: Balanceado Ponedora | C96: 64 | D96: =+[1]Egresos!E96/C96 -> 0
A97: 44974 | B97: Cubeta blanca | C97: =4*100 -> 400 | D97: =+[1]Egresos!E97/C97 -> 0
A98: 44974 | B98: Huevo B | C98: 25 | D98: =+#REF!/C98 -> #REF! | E98: Fredi
A99: 44974 | B99: Huevo C | C99: 24 | D99: =+#REF!/C99 -> #REF! | E99: Blanqui
A100: 44974 | B100: Huevo B | C100: 40 | D100: =+#REF!/C100 -> #REF! | E100: Blanqui
A101: 44974 | B101: Huevo A | C101: 2 | D101: =+#REF!/C101 -> #REF! | E101: Magali Ovelar
A102: 44975 | B102: Huevo A | C102: 10 | D102: =+#REF!/C102 -> #REF! | E102: Ña Ernesta
A103: 44975 | B103: Seltz | C103: 1 | D103: =+[1]Egresos!E103/C103 -> 0
...

Sheet Hoja1
A1: Fecha | B1: Ingreso | C1: Egreso | D1: Concepto | E1: Cantidad | F1: Precio Unitario | G1: Cliente | H1: Observaciones
B2: =+SUM(B3:B473) -> 33415000 | C2: =+SUM(C3:C451) -> 79839000
A3: 44805 | C3: 2600000 | D3: Cascarilla de arroz | E3: 1 | F3: 2600000
A4: 44816 | C4: 160000 | D4: AVT 40 | E4: 1 | F4: 160000 | G4: Cooka
A5: 44816 | C5: 348000 | D5: Poly-phen | E5: 1 | F5: 348000 | G5: Bionatural
A6: 44816 | C6: 157000 | D6: Potenbac polvo 100g | E6: 1 | F6: 157000 | G6: Bionatural
A7: 44816 | C7: 120000 | D7: Cables y portafoco
A8: 44817 | C8: 75000 | D8: Carpa negra 15x4
A9: 44788 | C9: 70000 | D9: Diluyente | E9: 2 | F9: 35000 | G9: Bionatural
A10: 44820 | C10: 14200000 | D10: Pollitas HyLine Brown | E10: 2000 | F10: =+C10/E10 -> 7100
A11: 44820 | C11: 730000 | D11: Balanceado Inicio | E11: 10 | F11: =+C11/E11 -> 73000 | G11: Cooka
A12: 44820 | C12: 60000 | D12: Maiz molido 30 kg | E12: 1 | G12: Cooka
A13: 44820 | C13: 245000 | D13: Stop Stress | E13: 1 | F13: 245000 | G13: Cooka
A14: 44820 | C14: 32000 | D14: Balanza miligramo
A15: 44820 | C15: 55000 | D15: Balde para agua | E15: 2 | F15: =+C15/E15 -> 27500
A16: 44820 | C16: 50000 | D16: Balde para agua | E16: 2 | F16: =+C16/E16 -> 25000
A17: 44826 | C17: 545000 | D17: Vacunas
A18: 44826 | C18: 1095000 | D18: Balanceado Inicio | E18: 15 | F18: =+C18/E18 -> 73000
A19: 44827 | C19: 60000 | D19: Personal vacunación | E19: 2 | F19: 30000
A20: 44834 | C20: 1460000 | D20: Balanceado Inicio | E20: 20 | F20: =+C20/E20 -> 73000
A21: 44834 | C21: 120000 | D21: Vacunas
A22: 44834 | C22: 120000 | D22: Personal control | E22: 2 | F22: 60000
A23: 44840 | C23: 270000 | D23: Bebederos pendulares | E23: 6 | F23: =+C23/E23 -> 45000
A24: 44841 | C24: 84000 | D24: Vacunas
A25: 44841 | C25: 1314000 | D25: Balanceado Inicio | E25: 18 | F25: =+C25/E25 -> 73000
A26: 44845 | C26: 60000 | D26: Personal vacunación | E26: 2 | F26: 30000
A27: 44848 | C27: 165000 | D27: Vacunas
A28: 44848 | C28: 1460000 | D28: Balanceado Inicio | E28: 20 | F28: =+C28/E28 -> 73000
A29: 44849 | C29: 140000 | D29: Vacunas
A30: 44852 | C30: 360000 | D30: Bebederos pendulares | E30: 8 | F30: =+C30/E30 -> 45000
A31: 44855 | C31: 1460000 | D31: Balanceado Inicio | E31: 20 | F31: =+C31/E31 -> 73000
A32: 44860 | C32: 720000 | D32: Despique | E32: 2000 | F32: =+C32/E32 -> 360
A33: 44860 | C33: 60000 | D33: Personal despique | E33: 1 | F33: 60000
A34: 44862 | C34: 1825000 | D34: Balanceado Inicio | E34: 25 | F34: =+C34/E34 -> 73000
A35: 44866 | C35: 115000 | D35: Febenlasca 1L | E35: 1 | F35: =+C35/E35 -> 115000
A36: 44869 | C36: 2190000 | D36: Balanceado Inicio | E36: 30 | F36: =+C36/E36 -> 73000
A37: 44877 | C37: 1800000 | D37: Balanceado Crecimiento | E37: 25 | F37: =+C37/E37 -> 72000
A38: 44883 | C38: 2520000 | D38: Balanceado Crecimiento | E38: 35 | F38: =+C38/E38 -> 72000
A39: 44891 | C39: 2160000 | D39: Balanceado Crecimiento | E39: 30 | F39: =+C39/E39 -> 72000
A40: 44893 | B40: 100000 | D40: Bolsas de balanceado | E40: 200 | F40: =+B40/E40 -> 500 | G40: Venialvos
A41: 44897 | C41: 2520000 | D41: Balanceado Crecimiento | E41: 35 | F41: =+C41/E41 -> 72000
A42: 44901 | B42: 50000 | D42: Bolsas de balanceado | E42: 100 | F42: =+B42/E42 -> 500
A43: 44904 | C43: 3024000 | D43: Balanceado Crecimiento | E43: 42 | F43: =+C43/E43 -> 72000
A44: 44912 | C44: 3024000 | D44: Balanceado Crecimiento | E44: 42 | F44: =+C44/E44 -> 72000
A45: 44916 | C45: 3024000 | D45: Balanceado Crecimiento | E45: 42 | F45: =+C45/E45 -> 72000
A46: 44924 | C46: 3024000 | D46: Balanceado Crecimiento | E46: 42 | F46: =+C46/E46 -> 72000
A47: 44932 | C47: 3024000 | D47: Balanceado Crecimiento | E47: 42 | F47: =+C47/E47 -> 72000
A48: 44939 | C48: 3456000 | D48: Balanceado Crecimiento | E48: 48 | F48: =+C48/E48 -> 72000
A49: 44946 | C49: =3528000+216000 -> 3744000 | D49: Balanceado Crecimiento | E49: 52 | F49: =+C49/E49 -> 72000
A50: 44950 | C50: 195000 | D50: Promotor L47 1 L | E50: 1 | F50: =+C50/E50 -> 195000
A51: 44953 | B51: 140000 | D51: Bolsas de balanceado | E51: 280 | F51: =+B51/E51 -> 500
A52: 44954 | C52: 3300000 | D52: Balanceado Ponedora | E52: 50 | F52: =+C52/E52 -> 66000
A53: 44956 | B53: 150000 | D53: Huevo C | E53: 10 | F53: =+B53/E53 -> 15000
A54: 44957 | B54: 20000 | D54: Huevo C | E54: 1 | F54: =+B54/E54 -> 20000
A55: 44958 | B55: 198000 | D55: Huevo C | E55: 11 | F55: =+B55/E55 -> 18000
A56: 44959 | B56: 10000 | D56: Huevo menudeo | E56: 15 | F56: =+B56/E56 -> 666.66667
A57: 44960 | C57: 3432000 | D57: Balanceado Ponedora | E57: 52 | F57: =+C57/E57 -> 66000
A58: 44962 | B58: 180000 | D58: Huevo B | E58: 10 | F58: =+B58/E58 -> 18000 | G58: Ani
A59: 44963 | B59: 595000 | D59: Huevo C | E59: 35 | F59: =+B59/E59 -> 17000 | G59: Coti
A60: 44963 | B60: 558000 | D60: Locote | E60: 124 | F60: =+B60/E60 -> 4500 | G60: Oscar
A61: 44963 | B61: 285000 | D61: Huevo B | E61: 15 | F61: =+B61/E61 -> 19000 | G61: Fredi | I61: =8.5*68000+60000+20000 -> 658000
A62: 44963 | B62: 25000 | D62: Locote | E62: 5 | F62: =+B62/E62 -> 5000 | G62: Fredi | I62: =I61/20 -> 32900
A63: 44963 | B63: 25000 | D63: Locote | E63: 5 | F63: =+B63/E63 -> 5000 | G63: Kiti
A64: 44964 | B64: 57000 | D64: Locote | E64: 11.5 | F64: =+B64/E64 -> 4956.5217 | G64: Kiti
A65: 44964 | B65: 89000 | D65: Huevo C | E65: 5 | F65: =+B65/E65 -> 17800 | G65: Kiti
A66: 44964 | B66: 80000 | D66: Locote | E66: 20 | F66: =+B66/E66 -> 4000 | G66: Ani
A67: 44964 | B67: 60000 | D67: Huevo B | E67: 3 | F67: =+B67/E67 -> 20000 | G67: Luz Villasanti
A68: 44964 | B68: 54000 | D68: Huevo B | E68: 3 | F68: =+B68/E68 -> 18000 | G68: Ani
A69: 44965 | B69: 90000 | D69: Huevo B | E69: 5 | F69: =+B69/E69 -> 18000 | G69: Ani
A70: 44967 | B70: 20000 | D70: Huevo B | E70: 1 | F70: =+B70/E70 -> 20000 | G70: Vecinos
A71: 44967 | B71: 42000 | D71: Huevo B | E71: 2 | F71: =+B71/E71 -> 21000 | G71: Panadería
A72: 44967 | B72: 200000 | D72: Huevo B | E72: 10 | F72: =+B72/E72 -> 20000 | G72: Ña Ernesta
A73: 44967 | C73: 4080000 | D73: Balanceado Ponedora | E73: 60 | F73: =+C73/E73 -> 68000 | G73: Cooka
A74: 44967 | C74: 104000 | D74: Cubetas | E74: =2*100 -> 200 | F74: =+C74/E74 -> 520 | G74: Cooka
A75: 44967 | B75: 20000 | D75: Huevo picado | E75: 2 | F75: =+B75/E75 -> 10000 | G75: Vecinos
A76: 44967 | B76: 425000 | D76: Huevo C | E76: 25 | F76: =+B76/E76 -> 17000 | G76: Coti
A77: 44969 | B77: 54000 | D77: Huevo C | E77: 3 | F77: =+B77/E77 -> 18000 | G77: Edelio
A78: 44970 | B78: 648000 | D78: Locote | E78: 162 | F78: =+B78/E78 -> 4000 | G78: Walter
A79: 44970 | B79: 90000 | D79: Huevo B | E79: 5 | F79: =+B79/E79 -> 18000 | G79: Ani
A80: 44970 | B80: 1000000 | D80: Huevo B | E80: 50 | F80: =+B80/E80 -> 20000 | G80: Dalila
A81: 44970 | B81: 418000 | D81: Huevo B | E81: 22 | F81: =+B81/E81 -> 19000 | G81: Fredi
A82: 44971 | B82: 418000 | D82: Huevo B | E82: 22 | F82: =+B82/E82 -> 19000 | G82: Fredi
A83: 44971 | B83: 105000 | D83: Huevo A | E83: 5 | F83: =+B83/E83 -> 21000 | G83: Ña Oso
A84: 44972 | B84: 10000 | D84: Huevo picado | E84: 1 | F84: =+B84/E84 -> 10000 | G84: Vecinos
A85: 44972 | C85: 104000 | D85: Cubeta blanca | E85: 200 | F85: =+C85/E85 -> 520 | G85: Cooka
A86: 44972 | C86: 84000 | D86: Cubeta verde | E86: 210 | F86: =+C86/E86 -> 400 | G86: Coti
A87: 44972 | B87: 765000 | D87: Huevo C | E87: 45 | F87: =+B87/E87 -> 17000 | G87: Coti | H87: falta pagar 281000
A88: 44973 | B88: 114000 | D88: Huevo C | E88: 6 | F88: =+B88/E88 -> 19000 | G88: Elsa
A89: 44973 | B89: 75000 | D89: Locote | E89: 15 | F89: =+B89/E89 -> 5000 | G89: Elsa
A90: 44973 | B90: 228000 | D90: Huevo B | E90: 12 | F90: =+B90/E90 -> 19000 | G90: Fredi
A91: 44973 | B91: 25000 | D91: Locote | E91: 5 | F91: =+B91/E91 -> 5000 | G91: Fredi
A92: 44973 | B92: 1000000 | D92: Huevo B | E92: 50 | F92: =+B92/E92 -> 20000 | G92: Dalila
A93: 44973 | B93: 44000 | D93: Huevo S | E93: 2 | F93: =+B93/E93 -> 22000
A94: 44973 | B94: 80000 | D94: Huevo A | E94: 4 | F94: =+B94/E94 -> 20000
A95: 44973 | B95: 60000 | D95: Huevo B | E95: 3 | F95: =+B95/E95 -> 20000
A96: 44974 | C96: 4352000 | D96: Balanceado Ponedora | E96: 64 | F96: =+C96/E96 -> 68000
A97: 44974 | C97: 208000 | D97: Cubeta blanca | E97: =4*100 -> 400 | F97: =+C97/E97 -> 520
A98: 44974 | B98: 475000 | D98: Huevo B | E98: 25 | F98: =+B98/E98 -> 19000 | G98: Fredi
A99: 44974 | B99: 456000 | D99: Huevo C | E99: 24 | F99: =+B99/E99 -> 19000 | G99: Blanqui
A100: 44974 | B100: 800000 | D100: Huevo B | E100: 40 | F100: =+B100/E100 -> 20000 | G100: Blanqui
...
